demux/__init__.py
demux/__main__.py
demux/cli/__init__.py
demux/cli/base.py
demux/cli/basemask.py
demux/cli/samplesheet.py
demux/utils/__init__.py
demux/utils/novaseq_samplesheet.py
demux/utils/runparameters.py
demux/utils/samplesheet.py
demux-5.4.5.dist-info/entry_points.txt
demux-5.4.5.dist-info/WHEEL
demux-5.4.5.dist-info/METADATA
demux-5.4.5.dist-info/RECORD
