Metadata-Version: 2.1
Name: demux
Version: 5.4.5
Summary: Application for demultiplexing sequence data
License: MIT
Author: henrikstranneheim
Author-email: henrik.stranneheim@scilifelab.se
Requires-Python: >=3.7,<4.0
Classifier: License :: OSI Approved :: MIT License
Classifier: Programming Language :: Python :: 3
Classifier: Programming Language :: Python :: 3.7
Classifier: Programming Language :: Python :: 3.8
Classifier: Programming Language :: Python :: 3.9
Requires-Dist: PyYAML (>=5.3.1,<6.0.0)
Requires-Dist: cglims (>=1.3.4,<2.0.0)
Requires-Dist: click (>=6.7.0,<7.0.0)
Requires-Dist: importlib-metadata (>=3.1.1,<4.0.0)
Requires-Dist: path.py (>=12.5.0,<13.0.0)
Requires-Dist: psutil (>=5.7.3,<6.0.0)
Requires-Dist: six (>=1.15.0,<2.0.0)
